[
  {
    "Ticker":"BPY6D",
    "Precio":"101.500",
    "Dif":"0.35%",
    "TIR":"-0.0%",
    "TEM":"-0.0%",
    "TNA":"-0.0%",
    "MD":"0.35",
    "Vol(M)":"1.1",
    "Paridad":"101.1%",
    "VT":"100.442",
    "TTir":"7.408",
    "upTTir":"-2.497",
    "dQ":"40",
    "dF":"221",
    "c($m)":"0.750",
    "cY(%)":"0.739"
  },
  {
    "Ticker":"BPD7D",
    "Precio":"89",
    "Dif":"-0.11%",
    "TIR":"14.3%",
    "TEM":"1.1%",
    "TNA":"13.4%",
    "MD":"1.55",
    "Vol(M)":"0.5",
    "Paridad":"86.9%",
    "VT":"102.403",
    "TTir":"9.161",
    "upTTir":"7.915",
    "dQ":"9",
    "dF":"739",
    "c($m)":"2.500",
    "cY(%)":"2.809"
  },
  {
    "Ticker":"BPC7D",
    "Precio":"89.240",
    "Dif":"0.61%",
    "TIR":"14.1%",
    "TEM":"1.1%",
    "TNA":"13.3%",
    "MD":"1.55",
    "Vol(M)":"2.0",
    "Paridad":"87.1%",
    "VT":"102.403",
    "TTir":"9.163",
    "upTTir":"7.623",
    "dQ":"9",
    "dF":"739",
    "c($m)":"2.500",
    "cY(%)":"2.801"
  },
  {
    "Ticker":"BPB7D",
    "Precio":"97.450",
    "Dif":"0.57%",
    "TIR":"8.2%",
    "TEM":"0.7%",
    "TNA":"7.9%",
    "MD":"1.60",
    "Vol(M)":"2.0",
    "Paridad":"95.2%",
    "VT":"102.403",
    "TTir":"9.203",
    "upTTir":"-1.504",
    "dQ":"9",
    "dF":"739",
    "c($m)":"2.500",
    "cY(%)":"2.565"
  },
  {
    "Ticker":"BPA7D",
    "Precio":"101.900",
    "Dif":"-0.10%",
    "TIR":"5.4%",
    "TEM":"0.4%",
    "TNA":"5.2%",
    "MD":"1.63",
    "Vol(M)":"0.1",
    "Paridad":"99.5%",
    "VT":"102.403",
    "TTir":"9.222",
    "upTTir":"-5.834",
    "dQ":"9",
    "dF":"739",
    "c($m)":"2.500",
    "cY(%)":"2.453"
  }
]