[
  {
    "Ticker":"BPY6D",
    "Precio":"69.180",
    "Dif":"-0.12%",
    "TIR":"-8.6%",
    "TEM":"-0.7%",
    "TNA":"-9.0%",
    "MD":"0.29",
    "Vol(M)":"0.1",
    "Paridad":"103.5%",
    "VT":"66.848",
    "TTir":"7.182",
    "upTTir":"-4.458",
    "dQ":"62",
    "dF":"152",
    "c($m)":"0.489",
    "cY(%)":"0.707"
  },
  {
    "Ticker":"BPD7D",
    "Precio":"98.070",
    "Dif":"0.21%",
    "TIR":"7.0%",
    "TEM":"0.6%",
    "TNA":"6.8%",
    "MD":"1.47",
    "Vol(M)":"0.4",
    "Paridad":"97.2%",
    "VT":"100.861",
    "TTir":"9.098",
    "upTTir":"-2.883",
    "dQ":"121",
    "dF":"670",
    "c($m)":"2.500",
    "cY(%)":"2.549"
  },
  {
    "Ticker":"BPC7D",
    "Precio":"98.110",
    "Dif":"-0.14%",
    "TIR":"7.0%",
    "TEM":"0.6%",
    "TNA":"6.8%",
    "MD":"1.47",
    "Vol(M)":"0.3",
    "Paridad":"97.3%",
    "VT":"100.861",
    "TTir":"9.098",
    "upTTir":"-2.923",
    "dQ":"121",
    "dF":"670",
    "c($m)":"2.500",
    "cY(%)":"2.548"
  },
  {
    "Ticker":"BPB7D",
    "Precio":"99.230",
    "Dif":"0.03%",
    "TIR":"6.2%",
    "TEM":"0.5%",
    "TNA":"6.0%",
    "MD":"1.48",
    "Vol(M)":"0.1",
    "Paridad":"98.4%",
    "VT":"100.861",
    "TTir":"9.103",
    "upTTir":"-4.026",
    "dQ":"121",
    "dF":"670",
    "c($m)":"2.500",
    "cY(%)":"2.519"
  },
  {
    "Ticker":"BPA7D",
    "Precio":"99.860",
    "Dif":"-0.34%",
    "TIR":"5.8%",
    "TEM":"0.5%",
    "TNA":"5.6%",
    "MD":"1.48",
    "Vol(M)":"0.0",
    "Paridad":"99.0%",
    "VT":"100.861",
    "TTir":"9.106",
    "upTTir":"-4.635",
    "dQ":"121",
    "dF":"670",
    "c($m)":"2.500",
    "cY(%)":"2.504"
  }
]