[
  {
    "Ticker":"M30A6",
    "Precio":"113.670",
    "Dif":"+0.12%",
    "TIR":"28.2%",
    "TEM":"2.1%",
    "TNA":"25.1%",
    "MD":"0.05",
    "Vol(M)":"6201.6",
    "Paridad":"100.5%",
    "VT":"113.124",
    "dQ":"24",
    "dF":"23",
    "c($m)":"15.464",
    "cY(%)":"13.604",
    "TIR-10":"+0.5%",
    "TIR-5":"+0.3%",
    "TIR-3":"+0.1%",
    "TIR-2":"+0.1%",
    "TIR-1":"+0.0%",
    "TIR+1":"-0.0%",
    "TIR+2":"-0.1%",
    "TIR+3":"-0.1%",
    "TIR+5":"-0.2%",
    "TIR+10":"-0.5%"
  },
  {
    "Ticker":"M31G6",
    "Precio":"118.351",
    "Dif":"+0.30%",
    "TIR":"31.5%",
    "TEM":"2.3%",
    "TNA":"27.7%",
    "MD":"0.30",
    "Vol(M)":"115.6",
    "Paridad":"101.9%",
    "VT":"116.194",
    "dQ":"147",
    "dF":"146",
    "c($m)":"32.058",
    "cY(%)":"27.088",
    "TIR-10":"+3.2%",
    "TIR-5":"+1.6%",
    "TIR-3":"+0.9%",
    "TIR-2":"+0.6%",
    "TIR-1":"+0.3%",
    "TIR+1":"-0.3%",
    "TIR+2":"-0.6%",
    "TIR+3":"-0.9%",
    "TIR+5":"-1.5%",
    "TIR+10":"-2.9%"
  },
  {
    "Ticker":"TMF27",
    "Precio":"109.850",
    "Dif":"+0.69%",
    "TIR":"33.3%",
    "TEM":"2.4%",
    "TNA":"29.1%",
    "MD":"0.67",
    "Vol(M)":"1624.8",
    "Paridad":"103.6%",
    "VT":"106.061",
    "dQ":"326",
    "dF":"325",
    "c($m)":"41.862",
    "cY(%)":"38.109",
    "TIR-10":"+7.2%",
    "TIR-5":"+3.5%",
    "TIR-3":"+2.0%",
    "TIR-2":"+1.4%",
    "TIR-1":"+0.7%",
    "TIR+1":"-0.7%",
    "TIR+2":"-1.3%",
    "TIR+3":"-2.0%",
    "TIR+5":"-3.2%",
    "TIR+10":"-6.2%"
  }
]