[
  {
    "Ticker":"T15D5",
    "Precio":"169.719",
    "Dif":"-0.02%",
    "TIR":"24.4%",
    "TEM":"1.8%",
    "TNA":"22.0%",
    "MD":"0.02",
    "Vol(M)":"3797.6",
    "Paridad":"100.4%",
    "VT":"168.987",
    "TTir":"32",
    "upTTir":"-0.179",
    "dQ":"12",
    "dF":"12",
    "c($m)":"70.838",
    "cY(%)":"41.739"
  },
  {
    "Ticker":"T13F6",
    "Precio":"137.538",
    "Dif":"0.05%",
    "TIR":"31.0%",
    "TEM":"2.3%",
    "TNA":"27.3%",
    "MD":"0.15",
    "Vol(M)":"77264.6",
    "Paridad":"99.8%",
    "VT":"137.817",
    "TTir":"32",
    "upTTir":"-0.141",
    "dQ":"72",
    "dF":"72",
    "c($m)":"44.966",
    "cY(%)":"32.693"
  },
  {
    "Ticker":"T30J6",
    "Precio":"123.850",
    "Dif":"0.16%",
    "TIR":"33.3%",
    "TEM":"2.4%",
    "TNA":"29.1%",
    "MD":"0.43",
    "Vol(M)":"5259.5",
    "Paridad":"96.9%",
    "VT":"127.829",
    "TTir":"32",
    "upTTir":"0.574",
    "dQ":"209",
    "dF":"209",
    "c($m)":"45.913",
    "cY(%)":"37.071"
  },
  {
    "Ticker":"TO26",
    "Precio":"91.390",
    "Dif":"-0.01%",
    "TIR":"32.2%",
    "TEM":"2.4%",
    "TNA":"28.3%",
    "MD":"0.72",
    "Vol(M)":"47.1",
    "Paridad":"89.6%",
    "VT":"102.024",
    "TTir":"32",
    "upTTir":"0.158",
    "dQ":"135",
    "dF":"318",
    "c($m)":"7.750",
    "cY(%)":"8.480"
  }
]