[
  {
    "Nombre":"BBAR",
    "Precio":15.17,
    "Var %":4.84
  },
  {
    "Nombre":"BMA",
    "Precio":75.35,
    "Var %":2.77
  },
  {
    "Nombre":"CEPU",
    "Precio":15.75,
    "Var %":2.37
  },
  {
    "Nombre":"CRESY",
    "Precio":11.51,
    "Var %":2.04
  },
  {
    "Nombre":"EDN",
    "Precio":27.82,
    "Var %":2.39
  },
  {
    "Nombre":"GGAL",
    "Precio":45.1,
    "Var %":2.05
  },
  {
    "Nombre":"IRS",
    "Precio":15.33,
    "Var %":0.99
  },
  {
    "Nombre":"LOMA",
    "Precio":10.59,
    "Var %":0.57
  },
  {
    "Nombre":"PAM",
    "Precio":83.9,
    "Var %":1.19
  },
  {
    "Nombre":"SUPV",
    "Precio":9.31,
    "Var %":2.87
  },
  {
    "Nombre":"TEO",
    "Precio":12.26,
    "Var %":5.24
  },
  {
    "Nombre":"TGS",
    "Precio":30.78,
    "Var %":1.89
  },
  {
    "Nombre":"TS",
    "Precio":54.29,
    "Var %":0.99
  },
  {
    "Nombre":"TX",
    "Precio":40.28,
    "Var %":1.03
  },
  {
    "Nombre":"YPF",
    "Precio":38.57,
    "Var %":5.15
  }
]