[
  {
    "Nombre":"A3",
    "Precio":3370.0,
    "Var %":-3.16
  },
  {
    "Nombre":"AGRO",
    "Precio":66.8,
    "Var %":-2.33
  },
  {
    "Nombre":"AUSO",
    "Precio":3895.0,
    "Var %":-2.74
  },
  {
    "Nombre":"BHIP",
    "Precio":467.0,
    "Var %":-2.7
  },
  {
    "Nombre":"BOLT",
    "Precio":56.6,
    "Var %":-2.07
  },
  {
    "Nombre":"BPAT",
    "Precio":2310.0,
    "Var %":-4.93
  },
  {
    "Nombre":"CADO",
    "Precio":545.0,
    "Var %":-3.19
  },
  {
    "Nombre":"CAPX",
    "Precio":5920.0,
    "Var %":-4.2
  },
  {
    "Nombre":"CARC",
    "Precio":31.0,
    "Var %":-4.9
  },
  {
    "Nombre":"CECO2",
    "Precio":512.0,
    "Var %":-3.93
  },
  {
    "Nombre":"CELU",
    "Precio":456.0,
    "Var %":-5.78
  },
  {
    "Nombre":"CGPA2",
    "Precio":2810.0,
    "Var %":-3.93
  },
  {
    "Nombre":"CTIO",
    "Precio":2315.0,
    "Var %":-4.92
  },
  {
    "Nombre":"CVH",
    "Precio":7180.0,
    "Var %":-2.04
  },
  {
    "Nombre":"DGCU2",
    "Precio":1970.0,
    "Var %":-2.71
  },
  {
    "Nombre":"DOME",
    "Precio":97.0,
    "Var %":21.55
  },
  {
    "Nombre":"FERR",
    "Precio":38.6,
    "Var %":-9.81
  },
  {
    "Nombre":"FIPL",
    "Precio":257.0,
    "Var %":-5.34
  },
  {
    "Nombre":"GAMI",
    "Precio":256.0,
    "Var %":2.19
  },
  {
    "Nombre":"GARO",
    "Precio":242.0,
    "Var %":0.62
  },
  {
    "Nombre":"GBAN",
    "Precio":2370.0,
    "Var %":-3.26
  },
  {
    "Nombre":"GCDI",
    "Precio":24.3,
    "Var %":-3.18
  },
  {
    "Nombre":"GCLA",
    "Precio":2530.0,
    "Var %":-1.17
  },
  {
    "Nombre":"GRIM",
    "Precio":2425.0,
    "Var %":-3.57
  },
  {
    "Nombre":"HARG",
    "Precio":1960.0,
    "Var %":-2.72
  },
  {
    "Nombre":"HAVA",
    "Precio":5960.0,
    "Var %":-5.84
  },
  {
    "Nombre":"IEB",
    "Precio":710.0,
    "Var %":-6.33
  },
  {
    "Nombre":"INAG",
    "Precio":7300.0,
    "Var %":0.0
  },
  {
    "Nombre":"INTR",
    "Precio":402.0,
    "Var %":-3.36
  },
  {
    "Nombre":"INVJ",
    "Precio":660.0,
    "Var %":-7.17
  },
  {
    "Nombre":"IRSA",
    "Precio":2185.0,
    "Var %":-2.01
  },
  {
    "Nombre":"LEDE",
    "Precio":1140.0,
    "Var %":-2.97
  },
  {
    "Nombre":"LONG",
    "Precio":27.8,
    "Var %":-4.13
  },
  {
    "Nombre":"MERA",
    "Precio":48.0,
    "Var %":0.0
  },
  {
    "Nombre":"MIRG",
    "Precio":23425.0,
    "Var %":-0.63
  },
  {
    "Nombre":"MOLA",
    "Precio":28050.0,
    "Var %":-3.1
  },
  {
    "Nombre":"MOLI",
    "Precio":3850.0,
    "Var %":-5.75
  },
  {
    "Nombre":"MORI",
    "Precio":49.9,
    "Var %":-3.66
  },
  {
    "Nombre":"OEST",
    "Precio":912.5,
    "Var %":-1.35
  },
  {
    "Nombre":"PATA",
    "Precio":1630.0,
    "Var %":-5.78
  },
  {
    "Nombre":"PGR",
    "Precio":24.6,
    "Var %":0.0
  },
  {
    "Nombre":"POLL",
    "Precio":325.5,
    "Var %":-1.21
  },
  {
    "Nombre":"RICH",
    "Precio":1875.0,
    "Var %":9.97
  },
  {
    "Nombre":"RIGO",
    "Precio":688.0,
    "Var %":-1.71
  },
  {
    "Nombre":"ROSE",
    "Precio":258.0,
    "Var %":10.49
  },
  {
    "Nombre":"SAMI",
    "Precio":820.0,
    "Var %":-8.88
  },
  {
    "Nombre":"SEMI",
    "Precio":30.5,
    "Var %":-1.29
  }
]