[
  {
    "Nombre":"ALUA",
    "Precio":1015.0,
    "Var %":0.89
  },
  {
    "Nombre":"ALUAD",
    "Precio":0.68,
    "Var %":-0.14
  },
  {
    "Nombre":"BBAR",
    "Precio":7505.0,
    "Var %":1.0
  },
  {
    "Nombre":"BBARD",
    "Precio":4.8,
    "Var %":-4.0
  },
  {
    "Nombre":"BMA",
    "Precio":11880.0,
    "Var %":1.26
  },
  {
    "Nombre":"BMA.D",
    "Precio":8.04,
    "Var %":1.25
  },
  {
    "Nombre":"BYMA",
    "Precio":287.0,
    "Var %":0.34
  },
  {
    "Nombre":"BYMAD",
    "Precio":0.2,
    "Var %":-1.01
  },
  {
    "Nombre":"CEPU",
    "Precio":2246.0,
    "Var %":2.88
  },
  {
    "Nombre":"CEPUD",
    "Precio":1.51,
    "Var %":2.38
  },
  {
    "Nombre":"COME",
    "Precio":73.8,
    "Var %":5.73
  },
  {
    "Nombre":"COMED",
    "Precio":0.05,
    "Var %":6.24
  },
  {
    "Nombre":"CRES",
    "Precio":1764.0,
    "Var %":1.08
  },
  {
    "Nombre":"CRESD",
    "Precio":1.16,
    "Var %":-0.85
  },
  {
    "Nombre":"ECOGD",
    "Precio":2.3,
    "Var %":1.76
  },
  {
    "Nombre":"EDN",
    "Precio":2465.0,
    "Var %":3.44
  },
  {
    "Nombre":"EDND",
    "Precio":1.65,
    "Var %":0.3
  },
  {
    "Nombre":"GGAL",
    "Precio":7610.0,
    "Var %":2.01
  },
  {
    "Nombre":"GGALD",
    "Precio":5.11,
    "Var %":0.78
  },
  {
    "Nombre":"IRSAD",
    "Precio":1.52,
    "Var %":0.0
  },
  {
    "Nombre":"LOMA",
    "Precio":3585.0,
    "Var %":3.01
  },
  {
    "Nombre":"LOMAD",
    "Precio":2.4,
    "Var %":2.12
  },
  {
    "Nombre":"METR",
    "Precio":2475.0,
    "Var %":3.29
  },
  {
    "Nombre":"METRD",
    "Precio":1.69,
    "Var %":2.73
  },
  {
    "Nombre":"PAMP",
    "Precio":5400.0,
    "Var %":1.88
  },
  {
    "Nombre":"PAMPD",
    "Precio":3.65,
    "Var %":1.81
  },
  {
    "Nombre":"SUPV",
    "Precio":3170.0,
    "Var %":1.11
  },
  {
    "Nombre":"SUPVD",
    "Precio":2.13,
    "Var %":0.0
  },
  {
    "Nombre":"TECO2",
    "Precio":3625.0,
    "Var %":1.89
  },
  {
    "Nombre":"TECOD",
    "Precio":2.3,
    "Var %":-5.54
  },
  {
    "Nombre":"TGN4D",
    "Precio":3.07,
    "Var %":3.02
  },
  {
    "Nombre":"TGNO4",
    "Precio":4472.5,
    "Var %":1.35
  },
  {
    "Nombre":"TGSU2",
    "Precio":9180.0,
    "Var %":2.11
  },
  {
    "Nombre":"TGSUD",
    "Precio":6.11,
    "Var %":-1.45
  },
  {
    "Nombre":"TRAN",
    "Precio":3500.0,
    "Var %":2.11
  },
  {
    "Nombre":"TRAND",
    "Precio":2.39,
    "Var %":4.13
  },
  {
    "Nombre":"TXAR",
    "Precio":800.0,
    "Var %":0.69
  },
  {
    "Nombre":"TXARD",
    "Precio":0.54,
    "Var %":-1.63
  },
  {
    "Nombre":"VALO",
    "Precio":480.0,
    "Var %":0.1
  },
  {
    "Nombre":"VALOD",
    "Precio":0.32,
    "Var %":0.31
  },
  {
    "Nombre":"YPFD",
    "Precio":55300.0,
    "Var %":1.32
  },
  {
    "Nombre":"YPFDD",
    "Precio":37.2,
    "Var %":0.16
  }
]